immersivepoints/__init__.py
immersivepoints-1.0.0.dist-info/LICENSE
immersivepoints-1.0.0.dist-info/METADATA
immersivepoints-1.0.0.dist-info/WHEEL
immersivepoints-1.0.0.dist-info/top_level.txt
immersivepoints-1.0.0.dist-info/RECORD
