Metadata-Version: 2.1
Name: immersivepoints
Version: 1.0.0
Summary: Render point clouds inline in Jupyter notebooks and in VR
Home-page: https://github.com/rmeertens/ImmersivePoints
Author: ImmersivePoints
Keywords: point cloud,visualization,3D,VR,jupyter
Classifier: Development Status :: 4 - Beta
Classifier: Intended Audience :: Science/Research
Classifier: License :: OSI Approved :: MIT License
Classifier: Programming Language :: Python :: 3
Classifier: Programming Language :: Python :: 3.7
Classifier: Programming Language :: Python :: 3.8
Classifier: Programming Language :: Python :: 3.9
Classifier: Programming Language :: Python :: 3.10
Classifier: Programming Language :: Python :: 3.11
Classifier: Topic :: Scientific/Engineering :: Visualization
Requires-Python: >=3.7
License-File: LICENSE
Requires-Dist: numpy
Requires-Dist: ipython
Provides-Extra: dev
Requires-Dist: jupyter ; extra == 'dev'
Requires-Dist: pytest ; extra == 'dev'
